mjx_safety_gym/__init__.py
mjx_safety_gym/collision.py
mjx_safety_gym/lidar.py
mjx_safety_gym/mjx_env.py
mjx_safety_gym/world.py
mjx_safety_gym/envs/go_to_goal.py
mjx_safety_gym/envs/xmls/point.xml
mjx_safety_gym-0.1.6.dist-info/licenses/LICENSE
mjx_safety_gym-0.1.6.dist-info/METADATA
mjx_safety_gym-0.1.6.dist-info/WHEEL
mjx_safety_gym-0.1.6.dist-info/top_level.txt
mjx_safety_gym-0.1.6.dist-info/RECORD
