Metadata-Version: 2.4
Name: mjx-safety-gym
Version: 0.1.6
Summary: MJX Safety Gym Environments
Author-email: Max van der Hart <your.email@example.com>
Project-URL: Homepage, https://github.com/mvdhart/mjx-safety-gym
Requires-Python: >=3.11
License-File: LICENSE
Requires-Dist: absl-py<3.0.0,>=2.2.2
Requires-Dist: etils==1.13.0
Requires-Dist: flax==0.10.6
Requires-Dist: jax==0.6.0
Requires-Dist: ml_collections==1.1.0
Requires-Dist: mujoco==3.3.2
Requires-Dist: mujoco_mjx==3.3.2
Requires-Dist: numpy==2.3.2
Requires-Dist: pynput==1.8.1
Requires-Dist: setuptools>=68.0.0
Dynamic: license-file
